odoo/addons/mail_restrict_follower_selection/README.rst
odoo/addons/mail_restrict_follower_selection/__init__.py
odoo/addons/mail_restrict_follower_selection/__manifest__.py
odoo/addons/mail_restrict_follower_selection/utils.py
odoo/addons/mail_restrict_follower_selection/data/ir_actions.xml
odoo/addons/mail_restrict_follower_selection/data/ir_config_parameter.xml
odoo/addons/mail_restrict_follower_selection/demo/ir_config_parameter_demo.xml
odoo/addons/mail_restrict_follower_selection/i18n/de.po
odoo/addons/mail_restrict_follower_selection/i18n/fr.po
odoo/addons/mail_restrict_follower_selection/i18n/hr.po
odoo/addons/mail_restrict_follower_selection/i18n/it.po
odoo/addons/mail_restrict_follower_selection/i18n/mail_restrict_follower_selection.pot
odoo/addons/mail_restrict_follower_selection/i18n/sl.po
odoo/addons/mail_restrict_follower_selection/models/__init__.py
odoo/addons/mail_restrict_follower_selection/models/mail_followers.py
odoo/addons/mail_restrict_follower_selection/models/mail_thread.py
odoo/addons/mail_restrict_follower_selection/models/mail_wizard_invite.py
odoo/addons/mail_restrict_follower_selection/readme/CONFIGURE.md
odoo/addons/mail_restrict_follower_selection/readme/CONTRIBUTORS.md
odoo/addons/mail_restrict_follower_selection/readme/DESCRIPTION.md
odoo/addons/mail_restrict_follower_selection/static/description/icon.png
odoo/addons/mail_restrict_follower_selection/static/description/index.html
odoo/addons/mail_restrict_follower_selection/tests/__init__.py
odoo/addons/mail_restrict_follower_selection/tests/test_mail_restrict_follower_selection.py
odoo_addon_mail_restrict_follower_selection-18.0.1.0.0.4.dist-info/METADATA
odoo_addon_mail_restrict_follower_selection-18.0.1.0.0.4.dist-info/WHEEL
odoo_addon_mail_restrict_follower_selection-18.0.1.0.0.4.dist-info/top_level.txt
odoo_addon_mail_restrict_follower_selection-18.0.1.0.0.4.dist-info/RECORD
